{"IcoMoonType":"selection","icons":[{"icon":{"paths":["M225.835 286.165l225.835 225.835-225.835 225.835c-16.683 16.683-16.683 43.691 0 60.331s43.691 16.683 60.331 0l225.835-225.835 225.835 225.835c16.683 16.683 43.691 16.683 60.331 0s16.683-43.691 0-60.331l-225.835-225.835 225.835-225.835c16.683-16.683 16.683-43.691 0-60.331s-43.691-16.683-60.331 0l-225.835 225.835-225.835-225.835c-16.683-16.683-43.691-16.683-60.331 0s-16.683 43.691 0 60.331z"],"attrs":[{}],"isMulticolor":false,"isMulticolor2":false,"tags":["x"],"grid":24},"attrs":[{}],"properties":{"order":1,"id":0,"prevSize":24,"code":59648,"name":"x"},"setIdx":0,"setId":0,"iconIdx":0}],"height":1024,"metadata":{"name":"icomoon"},"preferences":{"showGlyphs":true,"showCodes":true,"showQuickUse":true,"showQuickUse2":true,"showSVGs":true,"fontPref":{"prefix":"vp-icon-","metadata":{"fontFamily":"icomoon","majorVersion":1,"minorVersion":0},"metrics":{"emSize":1024,"baseline":6.25,"whitespace":50},"embed":false,"noie8":true,"ie7":false,"showSelector":true,"selector":"class","classSelector":".vp-icon","showMetrics":false,"showMetadata":false},"imagePref":{"prefix":"icon-","png":true,"useClassSelector":true,"color":0,"bgColor":16777215},"historySize":50}}